GlioMRInter/__init__.py
GlioMRInter/dataPreprocessing.py
GlioMRInter/dataVisualization.py
GlioMRInter/modelBuilding.py
GlioMRInter/test.py
GlioMRInter-1.0.dist-info/LICENSE
GlioMRInter-1.0.dist-info/METADATA
GlioMRInter-1.0.dist-info/WHEEL
GlioMRInter-1.0.dist-info/top_level.txt
GlioMRInter-1.0.dist-info/RECORD
